setup.py
src/twilio/__init__.py
src/twilio/account.py
src/twilio/base.py
src/twilio/message.py
src/twilio_api.egg-info/PKG-INFO
src/twilio_api.egg-info/SOURCES.txt
src/twilio_api.egg-info/dependency_links.txt
src/twilio_api.egg-info/not-zip-safe
src/twilio_api.egg-info/requires.txt
src/twilio_api.egg-info/top_level.txt